{
  "type": "movie",
  "name": "Oil Rush Trailer",
  "steam_appid": 81386,
  "required_age": 0,
  "is_free": false,
  "detailed_description": "",
  "about_the_game": "",
  "short_description": "",
  "fullgame": {
    "appid": "200390",
    "name": "Oil Rush"
  },
  "header_image": "https://steamcdn-a.akamaihd.net/steam/apps/81386/header.jpg?t=1447355270",
  "website": null,
  "pc_requirements": [],
  "mac_requirements": [],
  "linux_requirements": [],
  "developers": [
    "Unigine Corp."
  ],
  "publishers": [
    ""
  ],
  "package_groups": [],
  "platforms": {
    "windows": true,
    "mac": true,
    "linux": false
  },
  "release_date": {
    "coming_soon": false,
    "date": "25 Jan, 2012"
  },
  "support_info": {
    "url": "",
    "email": ""
  },
  "background": ""
}
