{
  "type": "game",
  "name": "Self-Reliance \u81ea\u6211\u6027\u8d56",
  "steam_appid": 1016110,
  "required_age": 0,
  "is_free": true,
  "detailed_description": "Self-Reliance is a game that uses interactive videos as the game content. It is a sex education game, the player will grow up with the game characters together. When there is a choice, the palyer's decision can shift the whole game.",
  "about_the_game": "Self-Reliance is a game that uses interactive videos as the game content. It is a sex education game, the player will grow up with the game characters together. When there is a choice, the palyer's decision can shift the whole game.",
  "short_description": "Self-Reliance\u662f\u4e00\u6b3e\u5168\u7a0b\u4f7f\u7528\u771f\u4eba\u5f71\u50cf\uff08\u65e0\u8272\u60c5\u5185\u5bb9\uff09\u4f5c\u4e3a\u6e38\u620f\u5185\u5bb9\u7684\u4e92\u52a8\u5f0f\u5192\u9669\u7c7b\u6e38\u620f\uff0c\u6216\u8005\u53ef\u4ee5\u79f0\u5b83\u4e3a\u4e92\u52a8\u5f0f\u5f71\u7247\u3002\u5b83\u662f\u4e0d\u66b4\u9732\u7684\u6027\u6559\u80b2\u6e38\u620f\uff0c\u73a9\u5bb6\u548c\u6e38\u620f\u4e3b\u89d2\u4e00\u540c\u6210\u957f\u3002\u9047\u5230\u4e00\u4e2a\u9009\u62e9\u65f6\uff0c\u73a9\u5bb6\u7684\u9009\u62e9\u5c06\u51b3\u5b9a\u6e38\u620f\u5b8c\u5168\u4e0d\u540c\u7684\u5bfc\u5411\uff0c\u5982\u679c\u662f\u9519\u8bef\u7684\u9009\u62e9\u4e5f\u4f1a\u9644\u5e26\u7740\u76f8\u5173\u7684\u4e13\u4e1a\u533b\u751f\u7684\u89e3\u7b54\u4ee5\u8fbe\u5230\u6559\u80b2\u7684\u76ee\u7684\u3002",
  "supported_languages": "Simplified Chinese<strong>*</strong>, English<br><strong>*</strong>languages with full audio support",
  "header_image": "https://steamcdn-a.akamaihd.net/steam/apps/1016110/header.jpg?t=1549658752",
  "website": "http://sex.chinathinksbig.org",
  "pc_requirements": {
    "minimum": "<strong>Minimum:</strong><br><ul class=\"bb_ul\"><li><strong>OS:</strong> Windows 7<br></li><li><strong>Processor:</strong> intel g4560<br></li><li><strong>Memory:</strong> 1 GB RAM<br></li><li><strong>Graphics:</strong> N/A<br></li><li><strong>DirectX:</strong> Version 9.0<br></li><li><strong>Storage:</strong> 3 GB available space<br></li><li><strong>Sound Card:</strong> N/A</li></ul>",
    "recommended": "<strong>Recommended:</strong><br><ul class=\"bb_ul\"><li><strong>OS:</strong> Windows 10<br></li><li><strong>Processor:</strong> intel i7 4790k<br></li><li><strong>Memory:</strong> 4 GB RAM<br></li><li><strong>Graphics:</strong> N/A<br></li><li><strong>DirectX:</strong> Version 11<br></li><li><strong>Storage:</strong> 3 GB available space<br></li><li><strong>Sound Card:</strong> N/A</li></ul>"
  },
  "mac_requirements": {
    "minimum": "<strong>Minimum:</strong><br><ul class=\"bb_ul\"><li><strong>OS:</strong> El Capitan<br></li><li><strong>Processor:</strong> intel g4560<br></li><li><strong>Memory:</strong> 1 GB RAM<br></li><li><strong>Graphics:</strong> N/A<br></li><li><strong>Storage:</strong> 3 GB available space<br></li><li><strong>Sound Card:</strong> N/A</li></ul>",
    "recommended": "<strong>Recommended:</strong><br><ul class=\"bb_ul\"><li><strong>OS:</strong> Mojave<br></li><li><strong>Processor:</strong> intel i7 4790k<br></li><li><strong>Memory:</strong> 4 GB RAM<br></li><li><strong>Graphics:</strong> N/A<br></li><li><strong>Storage:</strong> 3 GB available space<br></li><li><strong>Sound Card:</strong> N/A</li></ul>"
  },
  "linux_requirements": [],
  "developers": [
    "Eroducate"
  ],
  "publishers": [
    "Eroducate"
  ],
  "packages": [
    336748
  ],
  "package_groups": [],
  "platforms": {
    "windows": true,
    "mac": true,
    "linux": false
  },
  "categories": [
    {
      "id": 2,
      "description": "Single-player"
    }
  ],
  "genres": [
    {
      "id": "25",
      "description": "Adventure"
    }
  ],
  "screenshots": [
    {
      "id": 0,
      "path_thumbnail": "https://steamcdn-a.akamaihd.net/steam/apps/1016110/ss_91b2b23ef2833a02534851eef2c468c1decc37da.600x338.jpg?t=1549658752",
      "path_full": "https://steamcdn-a.akamaihd.net/steam/apps/1016110/ss_91b2b23ef2833a02534851eef2c468c1decc37da.1920x1080.jpg?t=1549658752"
    },
    {
      "id": 1,
      "path_thumbnail": "https://steamcdn-a.akamaihd.net/steam/apps/1016110/ss_30eafbdcfb1d56debe008f1683733b9d88ca1abe.600x338.jpg?t=1549658752",
      "path_full": "https://steamcdn-a.akamaihd.net/steam/apps/1016110/ss_30eafbdcfb1d56debe008f1683733b9d88ca1abe.1920x1080.jpg?t=1549658752"
    },
    {
      "id": 2,
      "path_thumbnail": "https://steamcdn-a.akamaihd.net/steam/apps/1016110/ss_d80d915340c7351c62f69906cd5706d71ffb82ed.600x338.jpg?t=1549658752",
      "path_full": "https://steamcdn-a.akamaihd.net/steam/apps/1016110/ss_d80d915340c7351c62f69906cd5706d71ffb82ed.1920x1080.jpg?t=1549658752"
    },
    {
      "id": 3,
      "path_thumbnail": "https://steamcdn-a.akamaihd.net/steam/apps/1016110/ss_09afb9d6aa9eecaaf4f196c95b17446059554207.600x338.jpg?t=1549658752",
      "path_full": "https://steamcdn-a.akamaihd.net/steam/apps/1016110/ss_09afb9d6aa9eecaaf4f196c95b17446059554207.1920x1080.jpg?t=1549658752"
    },
    {
      "id": 4,
      "path_thumbnail": "https://steamcdn-a.akamaihd.net/steam/apps/1016110/ss_4996010ef306f4a5ce91c9906d3f52119ffee788.600x338.jpg?t=1549658752",
      "path_full": "https://steamcdn-a.akamaihd.net/steam/apps/1016110/ss_4996010ef306f4a5ce91c9906d3f52119ffee788.1920x1080.jpg?t=1549658752"
    },
    {
      "id": 5,
      "path_thumbnail": "https://steamcdn-a.akamaihd.net/steam/apps/1016110/ss_4ccb956c38144c3c6cfd812e1cb591dc840340f6.600x338.jpg?t=1549658752",
      "path_full": "https://steamcdn-a.akamaihd.net/steam/apps/1016110/ss_4ccb956c38144c3c6cfd812e1cb591dc840340f6.1920x1080.jpg?t=1549658752"
    },
    {
      "id": 6,
      "path_thumbnail": "https://steamcdn-a.akamaihd.net/steam/apps/1016110/ss_56f834d0bac87ec483996e2e75d940d9a3be32c3.600x338.jpg?t=1549658752",
      "path_full": "https://steamcdn-a.akamaihd.net/steam/apps/1016110/ss_56f834d0bac87ec483996e2e75d940d9a3be32c3.1920x1080.jpg?t=1549658752"
    },
    {
      "id": 7,
      "path_thumbnail": "https://steamcdn-a.akamaihd.net/steam/apps/1016110/ss_d89a66bfaea62a5677635126dec81f2b4976a58e.600x338.jpg?t=1549658752",
      "path_full": "https://steamcdn-a.akamaihd.net/steam/apps/1016110/ss_d89a66bfaea62a5677635126dec81f2b4976a58e.1920x1080.jpg?t=1549658752"
    },
    {
      "id": 8,
      "path_thumbnail": "https://steamcdn-a.akamaihd.net/steam/apps/1016110/ss_6a1ef383a9b0699bae133297693f3545289916d8.600x338.jpg?t=1549658752",
      "path_full": "https://steamcdn-a.akamaihd.net/steam/apps/1016110/ss_6a1ef383a9b0699bae133297693f3545289916d8.1920x1080.jpg?t=1549658752"
    },
    {
      "id": 9,
      "path_thumbnail": "https://steamcdn-a.akamaihd.net/steam/apps/1016110/ss_ed9a548e4a6a7597e9b44930f459a7960c1909b6.600x338.jpg?t=1549658752",
      "path_full": "https://steamcdn-a.akamaihd.net/steam/apps/1016110/ss_ed9a548e4a6a7597e9b44930f459a7960c1909b6.1920x1080.jpg?t=1549658752"
    }
  ],
  "movies": [
    {
      "id": 256740561,
      "name": "Self-Reliance Promo Vid",
      "thumbnail": "https://steamcdn-a.akamaihd.net/steam/apps/256740561/movie.293x165.jpg?t=1548375698",
      "webm": {
        "480": "http://steamcdn-a.akamaihd.net/steam/apps/256740561/movie480.webm?t=1548375698",
        "max": "http://steamcdn-a.akamaihd.net/steam/apps/256740561/movie_max.webm?t=1548375698"
      },
      "highlight": true
    }
  ],
  "achievements": {
    "total": 0
  },
  "release_date": {
    "coming_soon": false,
    "date": "7 Feb, 2019"
  },
  "support_info": {
    "url": "http://sex.chinathinksbig.org",
    "email": "http://sex.chinathinksbig.org"
  },
  "background": "https://steamcdn-a.akamaihd.net/steam/apps/1016110/page_bg_generated_v6b.jpg?t=1549658752",
  "content_descriptors": {
    "ids": [
      1,
      5
    ],
    "notes": "Contains scenes of condoms, pills, and pregnancy test kit(ONLY WITH THESE ITEMS ALONE)"
  }
}
