{
  "type": "dlc",
  "name": "100% Orange Juice - Sora & Sham (Cuties) Character Pack",
  "steam_appid": 1101350,
  "required_age": 0,
  "is_free": false,
  "detailed_description": "This Extra Character Pack for 100% Orange Juice adds a new playable dual character - the idol pair Sham &amp; Sora (Cuties) finally takes to the stage! The new character pair comes fully voiced and ready to put on a live concert!<br><br><strong>Sora &amp; Sham (Cuties) Character Pack includes</strong>:<br><ul class=\"bb_ul\"><li>A unique new dual character: The Cuties play as one unit<br></li><li><strong>Sora</strong> is voiced by Maruyama Miki<br></li><li><strong>Sham</strong> is voiced by Fukuyama Saori<br></li><li>A unique new Hyper Card puts on a live concert!</li></ul><br>The new character duo is designed by Orange_Juice\u2019s original staff for the game\u2019s English Steam release, with character and hyper card art by Hono.",
  "about_the_game": "This Extra Character Pack for 100% Orange Juice adds a new playable dual character - the idol pair Sham &amp; Sora (Cuties) finally takes to the stage! The new character pair comes fully voiced and ready to put on a live concert!<br><br><strong>Sora &amp; Sham (Cuties) Character Pack includes</strong>:<br><ul class=\"bb_ul\"><li>A unique new dual character: The Cuties play as one unit<br></li><li><strong>Sora</strong> is voiced by Maruyama Miki<br></li><li><strong>Sham</strong> is voiced by Fukuyama Saori<br></li><li>A unique new Hyper Card puts on a live concert!</li></ul><br>The new character duo is designed by Orange_Juice\u2019s original staff for the game\u2019s English Steam release, with character and hyper card art by Hono.",
  "short_description": "This Extra Character Pack for 100% Orange Juice adds a new playable dual character - the idol pair Sham &amp; Sora (Cuties) finally takes to the stage! The new character pair comes fully voiced and ready to put on a live concert!",
  "fullgame": {
    "appid": "282800",
    "name": "100% Orange Juice"
  },
  "supported_languages": "English, Japanese<strong>*</strong>, Simplified Chinese, Traditional Chinese, Spanish - Spain, Korean, Portuguese - Brazil, Spanish - Latin America<br><strong>*</strong>languages with full audio support",
  "header_image": "https://steamcdn-a.akamaihd.net/steam/apps/1101350/header.jpg?t=1563211467",
  "website": "http://fruitbatfactory.com/100orange/",
  "pc_requirements": {
    "minimum": "<strong>Minimum:</strong><br><ul class=\"bb_ul\"><li><strong>OS:</strong> Windows XP/Vista/7/8/10<br></li><li><strong>Processor:</strong> Intel Pentium 2.0GHz or higher<br></li><li><strong>Memory:</strong> 1024 MB RAM<br></li><li><strong>Graphics:</strong> Direct3D compatible video card with 128MB memory or more<br></li><li><strong>DirectX:</strong> Version 9.0c<br></li><li><strong>Storage:</strong> 2 GB available space<br></li><li><strong>Sound Card:</strong> DirectSound compatible sound card</li></ul>"
  },
  "mac_requirements": [],
  "linux_requirements": [],
  "developers": [
    "Orange_Juice"
  ],
  "publishers": [
    "Fruitbat Factory"
  ],
  "price_overview": {
    "currency": "EUR",
    "initial": 159,
    "final": 159,
    "discount_percent": 0,
    "initial_formatted": "",
    "final_formatted": "1,59\u20ac"
  },
  "packages": [
    371776
  ],
  "package_groups": [
    {
      "name": "default",
      "title": "Buy 100% Orange Juice - Sora & Sham (Cuties) Character Pack",
      "description": "",
      "selection_text": "Select a purchase option",
      "save_text": "",
      "display_type": 0,
      "is_recurring_subscription": "false",
      "subs": [
        {
          "packageid": 371776,
          "percent_savings_text": "",
          "percent_savings": 0,
          "option_text": "100% Orange Juice - Sora & Sham (Cuties) Character Pack - 1,59\u20ac",
          "option_description": "",
          "can_get_free_license": "0",
          "is_free_license": false,
          "price_in_cents_with_discount": 159
        }
      ]
    }
  ],
  "platforms": {
    "windows": true,
    "mac": false,
    "linux": false
  },
  "categories": [
    {
      "id": 2,
      "description": "Single-player"
    },
    {
      "id": 1,
      "description": "Multi-player"
    },
    {
      "id": 21,
      "description": "Downloadable Content"
    },
    {
      "id": 22,
      "description": "Steam Achievements"
    },
    {
      "id": 29,
      "description": "Steam Trading Cards"
    },
    {
      "id": 23,
      "description": "Steam Cloud"
    },
    {
      "id": 8,
      "description": "Valve Anti-Cheat enabled"
    },
    {
      "id": 15,
      "description": "Stats"
    },
    {
      "id": 25,
      "description": "Steam Leaderboards"
    }
  ],
  "genres": [
    {
      "id": "23",
      "description": "Indie"
    },
    {
      "id": "2",
      "description": "Strategy"
    }
  ],
  "screenshots": [
    {
      "id": 0,
      "path_thumbnail": "https://steamcdn-a.akamaihd.net/steam/apps/1101350/ss_0dd14a4c54817c0a0bc1ee616f7c2ab02e1a81f9.600x338.jpg?t=1563211467",
      "path_full": "https://steamcdn-a.akamaihd.net/steam/apps/1101350/ss_0dd14a4c54817c0a0bc1ee616f7c2ab02e1a81f9.1920x1080.jpg?t=1563211467"
    },
    {
      "id": 1,
      "path_thumbnail": "https://steamcdn-a.akamaihd.net/steam/apps/1101350/ss_80ead2be21e1b83ebc213db83b0f48be47c21db0.600x338.jpg?t=1563211467",
      "path_full": "https://steamcdn-a.akamaihd.net/steam/apps/1101350/ss_80ead2be21e1b83ebc213db83b0f48be47c21db0.1920x1080.jpg?t=1563211467"
    },
    {
      "id": 2,
      "path_thumbnail": "https://steamcdn-a.akamaihd.net/steam/apps/1101350/ss_2ec605e03c16fb091df6aec86b8d1f06c5d17189.600x338.jpg?t=1563211467",
      "path_full": "https://steamcdn-a.akamaihd.net/steam/apps/1101350/ss_2ec605e03c16fb091df6aec86b8d1f06c5d17189.1920x1080.jpg?t=1563211467"
    },
    {
      "id": 3,
      "path_thumbnail": "https://steamcdn-a.akamaihd.net/steam/apps/1101350/ss_37fa369d5cc274f1a725dcc97679236884c59c97.600x338.jpg?t=1563211467",
      "path_full": "https://steamcdn-a.akamaihd.net/steam/apps/1101350/ss_37fa369d5cc274f1a725dcc97679236884c59c97.1920x1080.jpg?t=1563211467"
    }
  ],
  "movies": [
    {
      "id": 256754366,
      "name": "Sora & Sham (Cuties) Character Trailer",
      "thumbnail": "https://steamcdn-a.akamaihd.net/steam/apps/256754366/movie.293x165.jpg?t=1561488063",
      "webm": {
        "480": "http://steamcdn-a.akamaihd.net/steam/apps/256754366/movie480.webm?t=1561488063",
        "max": "http://steamcdn-a.akamaihd.net/steam/apps/256754366/movie_max.webm?t=1561488063"
      },
      "highlight": true
    }
  ],
  "achievements": {
    "total": 0
  },
  "release_date": {
    "coming_soon": false,
    "date": "25 Jun, 2019"
  },
  "support_info": {
    "url": "http://forum.fruitbatfactory.com/viewforum.php?id=10",
    "email": "support@fruitbatfactory.com"
  },
  "background": "https://steamcdn-a.akamaihd.net/steam/apps/1101350/page_bg_generated_v6b.jpg?t=1563211467",
  "content_descriptors": {
    "ids": [],
    "notes": null
  }
}
