{
  "type": "game",
  "name": "Squirm",
  "steam_appid": 778330,
  "required_age": 0,
  "is_free": false,
  "controller_support": "full",
  "dlc": [
    790010
  ],
  "detailed_description": "<strong>Welcome to the land of Squimlia!</strong><br>After a previous adventure, you and your rat friend stop for a snooze. When you wake up, the rat is gone and strange creatures have appeared across the land as if from out of nowhere! What has happened while you were asleep? Where is your rat friend?<br>Get to the bottom of these mysteries by squirming your way through tons of trap-infested levels!<br>7 Varying Worlds, 5 Different Bosses, and so much more!<br><br><strong>150+ levels of platforming madness</strong><br>I hope you have tough legs because boy, are you gonna be jumping a lot. Well, you could always just not jump if you enjoy being impaled by spikes, scorched by fireballs, blasted by eyeballs, beaten by enemies, sucked into black holes, getting gunned down by cannons, etc. Hey look on the bright side, at least there are plenty of cool guys you can find down here on your adventure, you should try talking to them every now and then because you don\u2019t have real friends! <br><br><strong>Enjoy your stay!</strong><br>Hey, it's not so bad down here once you realize the inevitability of your own death. But, despite the peril that lies just ahead, you feel something pushing you on, something calling to you. something about a rat... guess you'll just have to suck it up and find out for yourself!<br><br><strong> Easter Eggs and Achievements! </strong><br>All sorts of things catered for you lovely completionist type people out there!<br>40 Achievements!<br>Many Easter Eggs!<br><br><br><br><br><br><br><br><br>I\u0336\u0342\u0315\u0315\u033d\u030b\u0305\u0311\u033a\u0353\u0333\u031c\u0347\u0328\u031f\u032d\u032c\u0317t\u0337\u0346\u0303\u0344\u0358\u0358\u035b\u0344\u031e\u0359\u035a\u031c\u0316\u0347\u0321\u032c\u0322'\u0338\u034c\u035b\u0357\u035d\u034b\u0350\u030b\u0315\u0313\u034a\u0319\u0355\u0323\u0355\u0330\u0322\u0323\u032f\u0353\u031ds\u0335\u0352\u0310\u0303\u0343\u0301\u0345 \u0334\u033d\u0351\u030e\u0311\u035a\u0319\u0327\u032c\u0316\u032a\u033b\u0330\u0328\u032aw\u0335\u033f\u0342\u034b\u0360\u0344\u030b\u0308\u034c\u035b\u031a\u030e\u035d\u030e\u035d\u032e\u0354\u032a\u0349\u032ca\u0335\u0314\u0305\u0309\u030d\u0314\u0307\u031b\u0314\u0340\u0301\u0300\u0340\u0312\u0339\u0332\u032a\u034e\u032f\u0345\u0319\u0355\u0353\u033b\u031fr\u0336\u0358\u0306\u0315\u030e\u0358\u035b\u0309\u0344\u0352\u0304\u0344\u0350\u0330\u0347\u031e\u032a\u0325\u0345\u0326\u0356\u031d\u034dm\u0338\u0303\u0311\u030f\u0359\u0320\u0323\u032b i\u0337\u0303\u0308\u0313\u0305\u0350\u0316n\u0338\u0340\u034a\u034c\u0320\u0318\u0348\u0359\u0322\u031e \u0336\u034c\u0346\u030e\u030b\u0344\u030f\u030e\u0309\u033a\u0345\u0355\u0327\u0348\u0331\u0321h\u0335\u030d\u0312\u030c\u031a\u0300\u033d\u0351\u0342\u0311\u0346\u0316\u031c\u0319e\u0337\u030d\u0303\u030a\u0308\u0340\u0311\u033e\u034b\u0344\u0319\u032b\u035c\u032c\u0328\u032e\u032e\u032d\u0339\u0323\u0327r\u0334\u035de\u0337\u0313\u0313\u0314\u0360\u033f\u031a\u0315\u0358\u033d\u033e\u0340\u0346\u030f\u034e\u0353\u0327\u0339\u0316\u031e\u0316\u0325\u033c\u0339.\u0337\u0301\u0357\u031a\u0315\u0301\u030e\u0313\u0315\u030d\u0358\u035d\u0360\u0309",
  "about_the_game": "<strong>Welcome to the land of Squimlia!</strong><br>After a previous adventure, you and your rat friend stop for a snooze. When you wake up, the rat is gone and strange creatures have appeared across the land as if from out of nowhere! What has happened while you were asleep? Where is your rat friend?<br>Get to the bottom of these mysteries by squirming your way through tons of trap-infested levels!<br>7 Varying Worlds, 5 Different Bosses, and so much more!<br><br><strong>150+ levels of platforming madness</strong><br>I hope you have tough legs because boy, are you gonna be jumping a lot. Well, you could always just not jump if you enjoy being impaled by spikes, scorched by fireballs, blasted by eyeballs, beaten by enemies, sucked into black holes, getting gunned down by cannons, etc. Hey look on the bright side, at least there are plenty of cool guys you can find down here on your adventure, you should try talking to them every now and then because you don\u2019t have real friends! <br><br><strong>Enjoy your stay!</strong><br>Hey, it's not so bad down here once you realize the inevitability of your own death. But, despite the peril that lies just ahead, you feel something pushing you on, something calling to you. something about a rat... guess you'll just have to suck it up and find out for yourself!<br><br><strong> Easter Eggs and Achievements! </strong><br>All sorts of things catered for you lovely completionist type people out there!<br>40 Achievements!<br>Many Easter Eggs!<br><br><br><br><br><br><br><br><br>I\u0336\u0342\u0315\u0315\u033d\u030b\u0305\u0311\u033a\u0353\u0333\u031c\u0347\u0328\u031f\u032d\u032c\u0317t\u0337\u0346\u0303\u0344\u0358\u0358\u035b\u0344\u031e\u0359\u035a\u031c\u0316\u0347\u0321\u032c\u0322'\u0338\u034c\u035b\u0357\u035d\u034b\u0350\u030b\u0315\u0313\u034a\u0319\u0355\u0323\u0355\u0330\u0322\u0323\u032f\u0353\u031ds\u0335\u0352\u0310\u0303\u0343\u0301\u0345 \u0334\u033d\u0351\u030e\u0311\u035a\u0319\u0327\u032c\u0316\u032a\u033b\u0330\u0328\u032aw\u0335\u033f\u0342\u034b\u0360\u0344\u030b\u0308\u034c\u035b\u031a\u030e\u035d\u030e\u035d\u032e\u0354\u032a\u0349\u032ca\u0335\u0314\u0305\u0309\u030d\u0314\u0307\u031b\u0314\u0340\u0301\u0300\u0340\u0312\u0339\u0332\u032a\u034e\u032f\u0345\u0319\u0355\u0353\u033b\u031fr\u0336\u0358\u0306\u0315\u030e\u0358\u035b\u0309\u0344\u0352\u0304\u0344\u0350\u0330\u0347\u031e\u032a\u0325\u0345\u0326\u0356\u031d\u034dm\u0338\u0303\u0311\u030f\u0359\u0320\u0323\u032b i\u0337\u0303\u0308\u0313\u0305\u0350\u0316n\u0338\u0340\u034a\u034c\u0320\u0318\u0348\u0359\u0322\u031e \u0336\u034c\u0346\u030e\u030b\u0344\u030f\u030e\u0309\u033a\u0345\u0355\u0327\u0348\u0331\u0321h\u0335\u030d\u0312\u030c\u031a\u0300\u033d\u0351\u0342\u0311\u0346\u0316\u031c\u0319e\u0337\u030d\u0303\u030a\u0308\u0340\u0311\u033e\u034b\u0344\u0319\u032b\u035c\u032c\u0328\u032e\u032e\u032d\u0339\u0323\u0327r\u0334\u035de\u0337\u0313\u0313\u0314\u0360\u033f\u031a\u0315\u0358\u033d\u033e\u0340\u0346\u030f\u034e\u0353\u0327\u0339\u0316\u031e\u0316\u0325\u033c\u0339.\u0337\u0301\u0357\u031a\u0315\u0301\u030e\u0313\u0315\u030d\u0358\u035d\u0360\u0309",
  "short_description": "After a previous adventure, you and your rat friend stop for a snooze. When you wake up, the rat is gone and strange creatures have appeared across the land as if from out of nowhere! What has happened while you were asleep? Where is your rat friend?<br />\r\nGet to the bottom of these mysteries by squirming your way through tons of trap-infested levels!",
  "supported_languages": "English",
  "reviews": "\u201cI don't want to play your game. Go ask your mom.\u201d<br />\r\n??/10 \u2013 My Dad<br />\r\n<br />\r\n\u201cIt's really good.\u201d<br />\r\n10/10 \u2013 My Mom<br />\r\n<br />\r\n\u201cI am incredibly charmed by the whole thing. I find this a... oh fuck.\u201d<br />\r\nJim Sterling<br />\r\n",
  "header_image": "https://steamcdn-a.akamaihd.net/steam/apps/778330/header.jpg?t=1523198492",
  "website": null,
  "pc_requirements": {
    "minimum": "<strong>Minimum:</strong><br><ul class=\"bb_ul\"><li><strong>OS:</strong> Windows XP<br></li><li><strong>Processor:</strong> Intel Dual Core or Equivalent<br></li><li><strong>Memory:</strong> 4 GB RAM<br></li><li><strong>Graphics:</strong> DirectX 9 compatible video card<br></li><li><strong>DirectX:</strong> Version 9.0<br></li><li><strong>Storage:</strong> 150 MB available space<br></li><li><strong>Sound Card:</strong> On-board sound<br></li><li><strong>Additional Notes:</strong> As long as your computer isn't a potato you should be able to run this.</li></ul>",
    "recommended": "<strong>Recommended:</strong><br><ul class=\"bb_ul\"><li><strong>OS:</strong> Windows 7, Windows 8, Windows 10<br></li><li><strong>Processor:</strong> Intel Dual Core or Equivalent<br></li><li><strong>Memory:</strong> 4 GB RAM<br></li><li><strong>Graphics:</strong> DirectX 9 compatible video card<br></li><li><strong>DirectX:</strong> Version 9.0<br></li><li><strong>Storage:</strong> 150 MB available space<br></li><li><strong>Sound Card:</strong> On-board sound<br></li><li><strong>Additional Notes:</strong> As long as your computer isn't a potato you should be able to run this.</li></ul>"
  },
  "mac_requirements": {
    "minimum": "<strong>Minimum:</strong><br><ul class=\"bb_ul\"><li><strong>OS:</strong> OSX<br></li><li><strong>Processor:</strong> Intel Processor<br></li><li><strong>Memory:</strong> 4 GB RAM<br></li><li><strong>Graphics:</strong> Open GL<br></li><li><strong>Storage:</strong> 150 MB available space<br></li><li><strong>Sound Card:</strong> On-board sound<br></li><li><strong>Additional Notes:</strong> As long as your computer isn't a potato you should be able to run this.</li></ul>",
    "recommended": "<strong>Recommended:</strong><br><ul class=\"bb_ul\"><li><strong>OS:</strong> OSX<br></li><li><strong>Processor:</strong> Intel Processor<br></li><li><strong>Memory:</strong> 4 GB RAM<br></li><li><strong>Graphics:</strong> Open GL<br></li><li><strong>Storage:</strong> 150 MB available space<br></li><li><strong>Sound Card:</strong> On-board sound<br></li><li><strong>Additional Notes:</strong> As long as your computer isn't a potato you should be able to run this.</li></ul>"
  },
  "linux_requirements": {
    "minimum": "<strong>Minimum:</strong><br><ul class=\"bb_ul\"><li><strong>Memory:</strong> 4 GB RAM<br></li><li><strong>Storage:</strong> 150 GB available space<br></li><li><strong>Sound Card:</strong> On-board sound<br></li><li><strong>Additional Notes:</strong> As long as your computer isn't a potato you should be able to run this.</li></ul>",
    "recommended": "<strong>Recommended:</strong><br><ul class=\"bb_ul\"><li><strong>Memory:</strong> 4 GB RAM<br></li><li><strong>Storage:</strong> 150 GB available space<br></li><li><strong>Sound Card:</strong> On-board sound<br></li><li><strong>Additional Notes:</strong> As long as your computer isn't a potato you should be able to run this.</li></ul>"
  },
  "developers": [
    "Alex Carpenter"
  ],
  "publishers": [
    "Alex Carpenter"
  ],
  "price_overview": {
    "currency": "EUR",
    "initial": 199,
    "final": 199,
    "discount_percent": 0
  },
  "packages": [
    234089
  ],
  "package_groups": [
    {
      "name": "default",
      "title": "Buy Squirm",
      "description": "",
      "selection_text": "Select a purchase option",
      "save_text": "",
      "display_type": 0,
      "is_recurring_subscription": "false",
      "subs": [
        {
          "packageid": 234089,
          "percent_savings_text": "",
          "percent_savings": 0,
          "option_text": "SQUIRM - 1,99\u20ac",
          "option_description": "",
          "can_get_free_license": "0",
          "is_free_license": false,
          "price_in_cents_with_discount": 199
        }
      ]
    }
  ],
  "platforms": {
    "windows": true,
    "mac": true,
    "linux": true
  },
  "categories": [
    {
      "id": 2,
      "description": "Single-player"
    },
    {
      "id": 22,
      "description": "Steam Achievements"
    },
    {
      "id": 28,
      "description": "Full controller support"
    }
  ],
  "genres": [
    {
      "id": "25",
      "description": "Adventure"
    },
    {
      "id": "23",
      "description": "Indie"
    }
  ],
  "screenshots": [
    {
      "id": 0,
      "path_thumbnail": "https://steamcdn-a.akamaihd.net/steam/apps/778330/ss_4692c6c224c2d7001418508dd28d58bd659727e8.600x338.jpg?t=1523198492",
      "path_full": "https://steamcdn-a.akamaihd.net/steam/apps/778330/ss_4692c6c224c2d7001418508dd28d58bd659727e8.1920x1080.jpg?t=1523198492"
    },
    {
      "id": 1,
      "path_thumbnail": "https://steamcdn-a.akamaihd.net/steam/apps/778330/ss_b4a2333590780efaf4cb84e43b1ee3f4f4bb6241.600x338.jpg?t=1523198492",
      "path_full": "https://steamcdn-a.akamaihd.net/steam/apps/778330/ss_b4a2333590780efaf4cb84e43b1ee3f4f4bb6241.1920x1080.jpg?t=1523198492"
    },
    {
      "id": 2,
      "path_thumbnail": "https://steamcdn-a.akamaihd.net/steam/apps/778330/ss_4ed6d83bb5e3c8c7b6e69058feed4e1effb2e43e.600x338.jpg?t=1523198492",
      "path_full": "https://steamcdn-a.akamaihd.net/steam/apps/778330/ss_4ed6d83bb5e3c8c7b6e69058feed4e1effb2e43e.1920x1080.jpg?t=1523198492"
    },
    {
      "id": 3,
      "path_thumbnail": "https://steamcdn-a.akamaihd.net/steam/apps/778330/ss_3618a3eb44ea6fad8cc6a25f71ba1568327c53da.600x338.jpg?t=1523198492",
      "path_full": "https://steamcdn-a.akamaihd.net/steam/apps/778330/ss_3618a3eb44ea6fad8cc6a25f71ba1568327c53da.1920x1080.jpg?t=1523198492"
    },
    {
      "id": 4,
      "path_thumbnail": "https://steamcdn-a.akamaihd.net/steam/apps/778330/ss_12fa86b2f868643a96139ee4b4badcb8a55d77c4.600x338.jpg?t=1523198492",
      "path_full": "https://steamcdn-a.akamaihd.net/steam/apps/778330/ss_12fa86b2f868643a96139ee4b4badcb8a55d77c4.1920x1080.jpg?t=1523198492"
    },
    {
      "id": 5,
      "path_thumbnail": "https://steamcdn-a.akamaihd.net/steam/apps/778330/ss_55d235e70e54d77399941bc2e312d11c246fad79.600x338.jpg?t=1523198492",
      "path_full": "https://steamcdn-a.akamaihd.net/steam/apps/778330/ss_55d235e70e54d77399941bc2e312d11c246fad79.1920x1080.jpg?t=1523198492"
    },
    {
      "id": 6,
      "path_thumbnail": "https://steamcdn-a.akamaihd.net/steam/apps/778330/ss_24c5d22f172cf833864cefdf0bfacd15385f0877.600x338.jpg?t=1523198492",
      "path_full": "https://steamcdn-a.akamaihd.net/steam/apps/778330/ss_24c5d22f172cf833864cefdf0bfacd15385f0877.1920x1080.jpg?t=1523198492"
    }
  ],
  "movies": [
    {
      "id": 256709379,
      "name": "Squirm Release Trailer",
      "thumbnail": "https://steamcdn-a.akamaihd.net/steam/apps/256709379/movie.293x165.jpg?t=1519174969",
      "webm": {
        "480": "http://steamcdn-a.akamaihd.net/steam/apps/256709379/movie480.webm?t=1519174969",
        "max": "http://steamcdn-a.akamaihd.net/steam/apps/256709379/movie_max.webm?t=1519174969"
      },
      "highlight": true
    }
  ],
  "achievements": {
    "total": 43,
    "highlighted": [
      {
        "name": "Bear the arm.",
        "path": "https://steamcdn-a.akamaihd.net/steamcommunity/public/images/apps/778330/c312789b5a7c144ad571bae05dafbe480bfec213.jpg"
      },
      {
        "name": "A Little Something Extra",
        "path": "https://steamcdn-a.akamaihd.net/steamcommunity/public/images/apps/778330/9f69578764792abc97cb33e4e0303159dad1013c.jpg"
      },
      {
        "name": "The Technique",
        "path": "https://steamcdn-a.akamaihd.net/steamcommunity/public/images/apps/778330/61da02072cb64fc01b3d324d20615637686a01a8.jpg"
      },
      {
        "name": "Spooky Scary",
        "path": "https://steamcdn-a.akamaihd.net/steamcommunity/public/images/apps/778330/54376ed650d542c1b0a2f523cfaa2a2f7bfcfcce.jpg"
      },
      {
        "name": "Flabsent Minded",
        "path": "https://steamcdn-a.akamaihd.net/steamcommunity/public/images/apps/778330/d6b1dde25e296b06a2f9d7c22677de883f9d5029.jpg"
      },
      {
        "name": "Unblock Me Please!",
        "path": "https://steamcdn-a.akamaihd.net/steamcommunity/public/images/apps/778330/a67f51b06b628430e315716123619c1ad83a757f.jpg"
      },
      {
        "name": "A Familiar Rodent",
        "path": "https://steamcdn-a.akamaihd.net/steamcommunity/public/images/apps/778330/b1359d465ac6cd8c9562cb7e8896227ae5646921.jpg"
      },
      {
        "name": "Mean Green Flying Machine",
        "path": "https://steamcdn-a.akamaihd.net/steamcommunity/public/images/apps/778330/6585dbd918f3e8afe491683602bae0476e00260c.jpg"
      },
      {
        "name": "Skywocket to Heww",
        "path": "https://steamcdn-a.akamaihd.net/steamcommunity/public/images/apps/778330/f9634e83907e637eddb21f7d958d80521a0378e2.jpg"
      },
      {
        "name": "What's in the Box?",
        "path": "https://steamcdn-a.akamaihd.net/steamcommunity/public/images/apps/778330/8bb93e84e10535bd7dc4839921854e5b50bb4f0e.jpg"
      }
    ]
  },
  "release_date": {
    "coming_soon": false,
    "date": "23 Mar, 2018"
  },
  "support_info": {
    "url": "https://twitter.com/Alpenter",
    "email": "alpenter002@gmail.com"
  },
  "background": "https://steamcdn-a.akamaihd.net/steam/apps/778330/page_bg_generated_v6b.jpg?t=1523198492"
}
