{
  "type": "game",
  "name": "Praey for the Gods",
  "steam_appid": 494430,
  "required_age": 0,
  "is_free": false,
  "controller_support": "full",
  "detailed_description": "In Praey for the Gods, you play a lone hero sent to the edge of a dying world to discover the mystery behind a never-ending winter. Arriving with only the clothes on your back, you must survive the colossal dangers that you encounter. To restore balance and reclaim the land from the brink, you will be faced with questions that not even a God knows the answer to.",
  "about_the_game": "In Praey for the Gods, you play a lone hero sent to the edge of a dying world to discover the mystery behind a never-ending winter. Arriving with only the clothes on your back, you must survive the colossal dangers that you encounter. To restore balance and reclaim the land from the brink, you will be faced with questions that not even a God knows the answer to.",
  "short_description": "Praey for the Gods is a brutal journey set on a desolate frozen island, where your only chance of survival is to destroy the very gods you believe in.",
  "supported_languages": "English",
  "header_image": "https://steamcdn-a.akamaihd.net/steam/apps/494430/header.jpg?t=1510864121",
  "website": "http://www.praeyforthegods.com",
  "pc_requirements": {
    "minimum": "<strong>Minimum:</strong><br><ul class=\"bb_ul\"><li><strong>OS:</strong> 64-bit Windows 7<br></li><li><strong>Processor:</strong> Intel CPU Core i5-2500K 3.3GHz, AMD CPU Phenom II X4 940.<br></li><li><strong>Memory:</strong> 6 GB RAM<br></li><li><strong>Graphics:</strong> Nvidia GPU GeForce GTX 660 or AMD GPU Radeon HD 7870<br></li><li><strong>DirectX:</strong> Version 11<br></li><li><strong>Storage:</strong> 20 GB available space<br></li><li><strong>Additional Notes:</strong> DirectX 11 is necessary to run the game.</li></ul>",
    "recommended": "<strong>Recommended:</strong><br><ul class=\"bb_ul\"><li><strong>OS:</strong> 64-bit Windows 7 or 64-bit Windows 8 (8.1) or Windows 10<br></li><li><strong>Processor:</strong> Intel CPU Core i7 3770 3,4 GHz, AMD CPU AMD FX-8350 4 GHz<br></li><li><strong>Memory:</strong> 6 GB RAM<br></li><li><strong>Graphics:</strong> Nvidia GPU GeForce GTX 770 or AMD GPU Radeon R9 290<br></li><li><strong>DirectX:</strong> Version 11<br></li><li><strong>Storage:</strong> 20 GB available space<br></li><li><strong>Additional Notes:</strong> DirectX 11 is necessary to run the game.</li></ul>"
  },
  "mac_requirements": [],
  "linux_requirements": [],
  "developers": [
    "No Matter Studios"
  ],
  "publishers": [
    "No Matter Studios"
  ],
  "package_groups": [],
  "platforms": {
    "windows": true,
    "mac": false,
    "linux": false
  },
  "categories": [
    {
      "id": 2,
      "description": "Single-player"
    },
    {
      "id": 28,
      "description": "Full controller support"
    }
  ],
  "genres": [
    {
      "id": "1",
      "description": "Action"
    },
    {
      "id": "25",
      "description": "Adventure"
    },
    {
      "id": "23",
      "description": "Indie"
    },
    {
      "id": "3",
      "description": "RPG"
    },
    {
      "id": "28",
      "description": "Simulation"
    }
  ],
  "screenshots": [
    {
      "id": 0,
      "path_thumbnail": "https://steamcdn-a.akamaihd.net/steam/apps/494430/ss_aacd4518d4281087f588617761d43eba4fd87fb2.600x338.jpg?t=1510864121",
      "path_full": "https://steamcdn-a.akamaihd.net/steam/apps/494430/ss_aacd4518d4281087f588617761d43eba4fd87fb2.1920x1080.jpg?t=1510864121"
    },
    {
      "id": 1,
      "path_thumbnail": "https://steamcdn-a.akamaihd.net/steam/apps/494430/ss_f1a1eb61f5f8970d45a45c975bea027061f03c65.600x338.jpg?t=1510864121",
      "path_full": "https://steamcdn-a.akamaihd.net/steam/apps/494430/ss_f1a1eb61f5f8970d45a45c975bea027061f03c65.1920x1080.jpg?t=1510864121"
    },
    {
      "id": 2,
      "path_thumbnail": "https://steamcdn-a.akamaihd.net/steam/apps/494430/ss_ecc31279ca44cd3f4bb08651b5c892d77c35c78b.600x338.jpg?t=1510864121",
      "path_full": "https://steamcdn-a.akamaihd.net/steam/apps/494430/ss_ecc31279ca44cd3f4bb08651b5c892d77c35c78b.1920x1080.jpg?t=1510864121"
    },
    {
      "id": 3,
      "path_thumbnail": "https://steamcdn-a.akamaihd.net/steam/apps/494430/ss_86e1f6f62bd0c5dc97b58fb574431c02a2bb7ca7.600x338.jpg?t=1510864121",
      "path_full": "https://steamcdn-a.akamaihd.net/steam/apps/494430/ss_86e1f6f62bd0c5dc97b58fb574431c02a2bb7ca7.1920x1080.jpg?t=1510864121"
    },
    {
      "id": 4,
      "path_thumbnail": "https://steamcdn-a.akamaihd.net/steam/apps/494430/ss_db385e62b3c26e80f692822d47c121a0b81135b0.600x338.jpg?t=1510864121",
      "path_full": "https://steamcdn-a.akamaihd.net/steam/apps/494430/ss_db385e62b3c26e80f692822d47c121a0b81135b0.1920x1080.jpg?t=1510864121"
    },
    {
      "id": 5,
      "path_thumbnail": "https://steamcdn-a.akamaihd.net/steam/apps/494430/ss_dcb039ac453aa3aad471f30a22d06b44bfb676a6.600x338.jpg?t=1510864121",
      "path_full": "https://steamcdn-a.akamaihd.net/steam/apps/494430/ss_dcb039ac453aa3aad471f30a22d06b44bfb676a6.1920x1080.jpg?t=1510864121"
    },
    {
      "id": 6,
      "path_thumbnail": "https://steamcdn-a.akamaihd.net/steam/apps/494430/ss_609e26b8da956fe85fc96c584a2d9e7ece0813c9.600x338.jpg?t=1510864121",
      "path_full": "https://steamcdn-a.akamaihd.net/steam/apps/494430/ss_609e26b8da956fe85fc96c584a2d9e7ece0813c9.1920x1080.jpg?t=1510864121"
    },
    {
      "id": 7,
      "path_thumbnail": "https://steamcdn-a.akamaihd.net/steam/apps/494430/ss_3e5c88e6ed319d7d9c4fa695dfe81f88fe919ef5.600x338.jpg?t=1510864121",
      "path_full": "https://steamcdn-a.akamaihd.net/steam/apps/494430/ss_3e5c88e6ed319d7d9c4fa695dfe81f88fe919ef5.1920x1080.jpg?t=1510864121"
    },
    {
      "id": 8,
      "path_thumbnail": "https://steamcdn-a.akamaihd.net/steam/apps/494430/ss_4021d39696e9aed50a9aa119a2cfe00b8b4e64bf.600x338.jpg?t=1510864121",
      "path_full": "https://steamcdn-a.akamaihd.net/steam/apps/494430/ss_4021d39696e9aed50a9aa119a2cfe00b8b4e64bf.1920x1080.jpg?t=1510864121"
    },
    {
      "id": 9,
      "path_thumbnail": "https://steamcdn-a.akamaihd.net/steam/apps/494430/ss_e2f8b6bec100e1a529b90716268f7a7844153724.600x338.jpg?t=1510864121",
      "path_full": "https://steamcdn-a.akamaihd.net/steam/apps/494430/ss_e2f8b6bec100e1a529b90716268f7a7844153724.1920x1080.jpg?t=1510864121"
    }
  ],
  "movies": [
    {
      "id": 256666677,
      "name": "Praey for the Gods Trailer 2",
      "thumbnail": "https://steamcdn-a.akamaihd.net/steam/apps/256666677/movie.293x165.jpg?t=1510864106",
      "webm": {
        "480": "http://steamcdn-a.akamaihd.net/steam/apps/256666677/movie480.webm?t=1510864106",
        "max": "http://steamcdn-a.akamaihd.net/steam/apps/256666677/movie_max.webm?t=1510864106"
      },
      "highlight": true
    },
    {
      "id": 256666479,
      "name": "Praey for the Gods Trailer 1",
      "thumbnail": "https://steamcdn-a.akamaihd.net/steam/apps/256666479/movie.293x165.jpg?t=1510864115",
      "webm": {
        "480": "http://steamcdn-a.akamaihd.net/steam/apps/256666479/movie480.webm?t=1510864115",
        "max": "http://steamcdn-a.akamaihd.net/steam/apps/256666479/movie_max.webm?t=1510864115"
      },
      "highlight": true
    }
  ],
  "release_date": {
    "coming_soon": true,
    "date": "2018"
  },
  "support_info": {
    "url": "",
    "email": "support@nomatterstudios.com"
  },
  "background": "https://steamcdn-a.akamaihd.net/steam/apps/494430/page_bg_generated_v6b.jpg?t=1510864121"
}
