{
  "type": "game",
  "name": "Sticks",
  "steam_appid": 715340,
  "required_age": 0,
  "is_free": false,
  "controller_support": "full",
  "dlc": [
    717900
  ],
  "detailed_description": "Sticks - very simple game. You must avoid sticks of the opposite color. Each press changes the direction of travel. The complexity of the game will gradually increase. Hone your skills!<br><strong>Features:</strong><br><ul class=\"bb_ul\"><li> Easy controls<br></li><li> Few difficulty levels<br></li><li> Changeable background<br></li><li> Pleasant soundtrack</li></ul>",
  "about_the_game": "Sticks - very simple game. You must avoid sticks of the opposite color. Each press changes the direction of travel. The complexity of the game will gradually increase. Hone your skills!<br><strong>Features:</strong><br><ul class=\"bb_ul\"><li> Easy controls<br></li><li> Few difficulty levels<br></li><li> Changeable background<br></li><li> Pleasant soundtrack</li></ul>",
  "short_description": "Sticks - very simple game. You must avoid sticks of the opposite color.",
  "supported_languages": "English",
  "header_image": "https://steamcdn-a.akamaihd.net/steam/apps/715340/header.jpg?t=1506956992",
  "website": null,
  "pc_requirements": {
    "minimum": "<strong>Minimum:</strong><br><ul class=\"bb_ul\"><li><strong>OS:</strong> Windows XP<br></li><li><strong>Processor:</strong> 1 GHZ<br></li><li><strong>Memory:</strong> 512 MB RAM<br></li><li><strong>Graphics:</strong> 512 MB<br></li><li><strong>Storage:</strong> 600 MB available space</li></ul>"
  },
  "mac_requirements": [],
  "linux_requirements": [],
  "developers": [
    "Striped Rocket"
  ],
  "publishers": [
    "Striped Rocket"
  ],
  "price_overview": {
    "currency": "EUR",
    "initial": 199,
    "final": 199,
    "discount_percent": 0
  },
  "packages": [
    207114
  ],
  "package_groups": [
    {
      "name": "default",
      "title": "Buy Sticks",
      "description": "",
      "selection_text": "Select a purchase option",
      "save_text": "",
      "display_type": 0,
      "is_recurring_subscription": "false",
      "subs": [
        {
          "packageid": 207114,
          "percent_savings_text": "",
          "percent_savings": 0,
          "option_text": "Sticks - 1,99\u20ac",
          "option_description": "",
          "can_get_free_license": "0",
          "is_free_license": false,
          "price_in_cents_with_discount": 199
        }
      ]
    }
  ],
  "platforms": {
    "windows": true,
    "mac": false,
    "linux": false
  },
  "categories": [
    {
      "id": 2,
      "description": "Single-player"
    },
    {
      "id": 22,
      "description": "Steam Achievements"
    },
    {
      "id": 28,
      "description": "Full controller support"
    },
    {
      "id": 29,
      "description": "Steam Trading Cards"
    },
    {
      "id": 25,
      "description": "Steam Leaderboards"
    }
  ],
  "genres": [
    {
      "id": "4",
      "description": "Casual"
    },
    {
      "id": "23",
      "description": "Indie"
    }
  ],
  "screenshots": [
    {
      "id": 0,
      "path_thumbnail": "https://steamcdn-a.akamaihd.net/steam/apps/715340/ss_7a73bfd6d2675025d4a5bd1ef11a767e7a6eea53.600x338.jpg?t=1506956992",
      "path_full": "https://steamcdn-a.akamaihd.net/steam/apps/715340/ss_7a73bfd6d2675025d4a5bd1ef11a767e7a6eea53.1920x1080.jpg?t=1506956992"
    },
    {
      "id": 1,
      "path_thumbnail": "https://steamcdn-a.akamaihd.net/steam/apps/715340/ss_1f34a228cdf34f1fea7aba04d7c03ee363549f95.600x338.jpg?t=1506956992",
      "path_full": "https://steamcdn-a.akamaihd.net/steam/apps/715340/ss_1f34a228cdf34f1fea7aba04d7c03ee363549f95.1920x1080.jpg?t=1506956992"
    },
    {
      "id": 2,
      "path_thumbnail": "https://steamcdn-a.akamaihd.net/steam/apps/715340/ss_d5dca49a9b31f0036f2e3639c61952b7052dc950.600x338.jpg?t=1506956992",
      "path_full": "https://steamcdn-a.akamaihd.net/steam/apps/715340/ss_d5dca49a9b31f0036f2e3639c61952b7052dc950.1920x1080.jpg?t=1506956992"
    },
    {
      "id": 3,
      "path_thumbnail": "https://steamcdn-a.akamaihd.net/steam/apps/715340/ss_1b02297719718dbc8a9575cca7fc616ecb3a88a5.600x338.jpg?t=1506956992",
      "path_full": "https://steamcdn-a.akamaihd.net/steam/apps/715340/ss_1b02297719718dbc8a9575cca7fc616ecb3a88a5.1920x1080.jpg?t=1506956992"
    },
    {
      "id": 4,
      "path_thumbnail": "https://steamcdn-a.akamaihd.net/steam/apps/715340/ss_6407cb34a9ab2a74771322154f602bee5be24a46.600x338.jpg?t=1506956992",
      "path_full": "https://steamcdn-a.akamaihd.net/steam/apps/715340/ss_6407cb34a9ab2a74771322154f602bee5be24a46.1920x1080.jpg?t=1506956992"
    }
  ],
  "movies": [
    {
      "id": 256695236,
      "name": "Sticks",
      "thumbnail": "https://steamcdn-a.akamaihd.net/steam/apps/256695236/movie.293x165.jpg?t=1505787621",
      "webm": {
        "480": "http://steamcdn-a.akamaihd.net/steam/apps/256695236/movie480.webm?t=1505787621",
        "max": "http://steamcdn-a.akamaihd.net/steam/apps/256695236/movie_max.webm?t=1505787621"
      },
      "highlight": true
    }
  ],
  "achievements": {
    "total": 10,
    "highlighted": [
      {
        "name": "100",
        "path": "https://steamcdn-a.akamaihd.net/steamcommunity/public/images/apps/715340/1f37e92afe59cd305fd03df3ce2dc2b67000041b.jpg"
      },
      {
        "name": "100",
        "path": "https://steamcdn-a.akamaihd.net/steamcommunity/public/images/apps/715340/22c1472d0fd67fb6deb548784b45ae898527084f.jpg"
      },
      {
        "name": "100",
        "path": "https://steamcdn-a.akamaihd.net/steamcommunity/public/images/apps/715340/7b9fbd5aa67ded3113886cc3c86039666da1b90d.jpg"
      },
      {
        "name": "100",
        "path": "https://steamcdn-a.akamaihd.net/steamcommunity/public/images/apps/715340/f6f28b1125ec29ca3ce6c3be6863ace2f0d5b67f.jpg"
      },
      {
        "name": "100",
        "path": "https://steamcdn-a.akamaihd.net/steamcommunity/public/images/apps/715340/dc29d576ce94871f2df7e33c7f2217bd7a903afe.jpg"
      },
      {
        "name": "500",
        "path": "https://steamcdn-a.akamaihd.net/steamcommunity/public/images/apps/715340/a4a78d24e89f4f5cf5ebe02fde8351d7d66d964d.jpg"
      },
      {
        "name": "500",
        "path": "https://steamcdn-a.akamaihd.net/steamcommunity/public/images/apps/715340/2d08a3d6e6b213bcecacd6e19b517c94360101ab.jpg"
      },
      {
        "name": "500",
        "path": "https://steamcdn-a.akamaihd.net/steamcommunity/public/images/apps/715340/60a438a71b68769406b4532ebf797aa9190dbdac.jpg"
      },
      {
        "name": "500",
        "path": "https://steamcdn-a.akamaihd.net/steamcommunity/public/images/apps/715340/18028725a2212cbf9d26c10612bf9ef5cc91fec1.jpg"
      },
      {
        "name": "500",
        "path": "https://steamcdn-a.akamaihd.net/steamcommunity/public/images/apps/715340/e3232fa75c682bb215cce7bde26adf394ba7afbb.jpg"
      }
    ]
  },
  "release_date": {
    "coming_soon": false,
    "date": "2 Oct, 2017"
  },
  "support_info": {
    "url": "",
    "email": "stripedrocketsup@gmail.com"
  },
  "background": "https://steamcdn-a.akamaihd.net/steam/apps/715340/page_bg_generated_v6b.jpg?t=1506956992"
}
