{
  "type": "game",
  "name": "Cross Country Skiing VR",
  "steam_appid": 834000,
  "required_age": 0,
  "is_free": false,
  "detailed_description": "Welcome to Cross Country Skiing VR! <br />\r\n<br />\r\nYour task is to finish before your opponent in a virtual, cross country skiing race. But watch out! You're ski poles are very short so squat down and really get moving with your arms to get a head start and cross the finish line first. You choose if you want to face off your opponent in a 500 or a 1 000 meter track. Get your heart rate going in the snowy, virtual forest tracks!",
  "about_the_game": "Welcome to Cross Country Skiing VR! <br />\r\n<br />\r\nYour task is to finish before your opponent in a virtual, cross country skiing race. But watch out! You're ski poles are very short so squat down and really get moving with your arms to get a head start and cross the finish line first. You choose if you want to face off your opponent in a 500 or a 1 000 meter track. Get your heart rate going in the snowy, virtual forest tracks!",
  "short_description": "Cross Country Skiing VR is a virtual, cross country skiing race where your task is to cross the finish line before your opponent. But watch out! Your ski poles are very short so be ready to squat down get moving with your arms to have a fair chance at the win!",
  "supported_languages": "English<strong>*</strong><br><strong>*</strong>languages with full audio support",
  "header_image": "https://steamcdn-a.akamaihd.net/steam/apps/834000/header.jpg?t=1523566258",
  "website": null,
  "pc_requirements": {
    "minimum": "<strong>Minimum:</strong><br><ul class=\"bb_ul\"><li><strong>OS:</strong> Windows 10 or later<br></li><li><strong>Processor:</strong> Intel Core i7 6:e gen. 6700 equivalent or greater<br></li><li><strong>Memory:</strong> 4 GB RAM<br></li><li><strong>Graphics:</strong> NVIDIA GeForce GTX 1060 equivalent or greater<br></li><li><strong>DirectX:</strong> Version 11<br></li><li><strong>Storage:</strong> 200 MB available space<br></li><li><strong>Additional Notes:</strong> VR ONLY</li></ul>"
  },
  "mac_requirements": [],
  "linux_requirements": [],
  "legal_notice": "All rights reserved Levrage 2018",
  "developers": [
    "Levrage"
  ],
  "publishers": [
    "Levrage"
  ],
  "price_overview": {
    "currency": "EUR",
    "initial": 499,
    "final": 299,
    "discount_percent": 40
  },
  "packages": [
    258310
  ],
  "package_groups": [
    {
      "name": "default",
      "title": "Buy Cross Country Skiing VR",
      "description": "",
      "selection_text": "Select a purchase option",
      "save_text": "",
      "display_type": 0,
      "is_recurring_subscription": "false",
      "subs": [
        {
          "packageid": 258310,
          "percent_savings_text": "-40%",
          "percent_savings": 0,
          "option_text": "Cross Country Skiing VR - <span class=\"discount_original_price\">4,99\u20ac</span> 2,99\u20ac",
          "option_description": "",
          "can_get_free_license": "0",
          "is_free_license": false,
          "price_in_cents_with_discount": 299
        }
      ]
    }
  ],
  "platforms": {
    "windows": true,
    "mac": false,
    "linux": false
  },
  "categories": [
    {
      "id": 2,
      "description": "Single-player"
    }
  ],
  "genres": [
    {
      "id": "9",
      "description": "Racing"
    },
    {
      "id": "18",
      "description": "Sports"
    }
  ],
  "screenshots": [
    {
      "id": 0,
      "path_thumbnail": "https://steamcdn-a.akamaihd.net/steam/apps/834000/ss_bb5c5274e45be69964886e1f347517817dc080a6.600x338.jpg?t=1523566258",
      "path_full": "https://steamcdn-a.akamaihd.net/steam/apps/834000/ss_bb5c5274e45be69964886e1f347517817dc080a6.1920x1080.jpg?t=1523566258"
    },
    {
      "id": 1,
      "path_thumbnail": "https://steamcdn-a.akamaihd.net/steam/apps/834000/ss_121864f0cf05bab2beb99977f1f94891e0865610.600x338.jpg?t=1523566258",
      "path_full": "https://steamcdn-a.akamaihd.net/steam/apps/834000/ss_121864f0cf05bab2beb99977f1f94891e0865610.1920x1080.jpg?t=1523566258"
    },
    {
      "id": 2,
      "path_thumbnail": "https://steamcdn-a.akamaihd.net/steam/apps/834000/ss_64936ffa431f5339f788e7d65f3eda0b35658dea.600x338.jpg?t=1523566258",
      "path_full": "https://steamcdn-a.akamaihd.net/steam/apps/834000/ss_64936ffa431f5339f788e7d65f3eda0b35658dea.1920x1080.jpg?t=1523566258"
    },
    {
      "id": 3,
      "path_thumbnail": "https://steamcdn-a.akamaihd.net/steam/apps/834000/ss_f52ebbc021cbc472034d4221ecbb29d147c83f97.600x338.jpg?t=1523566258",
      "path_full": "https://steamcdn-a.akamaihd.net/steam/apps/834000/ss_f52ebbc021cbc472034d4221ecbb29d147c83f97.1920x1080.jpg?t=1523566258"
    },
    {
      "id": 4,
      "path_thumbnail": "https://steamcdn-a.akamaihd.net/steam/apps/834000/ss_6333dc5a85769baf62375cdc358042d23bd0f16c.600x338.jpg?t=1523566258",
      "path_full": "https://steamcdn-a.akamaihd.net/steam/apps/834000/ss_6333dc5a85769baf62375cdc358042d23bd0f16c.1920x1080.jpg?t=1523566258"
    }
  ],
  "movies": [
    {
      "id": 256713066,
      "name": "Cross Country Skiing VR",
      "thumbnail": "https://steamcdn-a.akamaihd.net/steam/apps/256713066/movie.293x165.jpg?t=1523483188",
      "webm": {
        "480": "http://steamcdn-a.akamaihd.net/steam/apps/256713066/movie480.webm?t=1523483188",
        "max": "http://steamcdn-a.akamaihd.net/steam/apps/256713066/movie_max.webm?t=1523483188"
      },
      "highlight": true
    }
  ],
  "release_date": {
    "coming_soon": false,
    "date": "12 Apr, 2018"
  },
  "support_info": {
    "url": "www.levrage.se/gamesupport",
    "email": "info@levrage.se"
  },
  "background": "https://steamcdn-a.akamaihd.net/steam/apps/834000/page_bg_generated_v6b.jpg?t=1523566258"
}
